rgroq/README.md
rgroq/__init__.py
rgroq/config.py
rgroq/main.py
rgroq/requirements.txt
rgroq/audio/notification1_mild.mp3
rgroq/audio/notification2_mild.mp3
rgroq/temp/Readme.md
rgroq/utils/promptValidator.py
rgroq/utils/single_prompt.py
rgroq/utils/streaming_word_wrapper.py
rgroq/utils/terminal_mode_dialogs.py
rgroq/utils/tts_utils.py
rgroq-2.3.0.dist-info/METADATA
rgroq-2.3.0.dist-info/WHEEL
rgroq-2.3.0.dist-info/entry_points.txt
rgroq-2.3.0.dist-info/top_level.txt
rgroq-2.3.0.dist-info/RECORD
