Metadata-Version: 2.2
Name: rgroq
Version: 2.3.0
Summary: A terminal chatbot, powered by Groq Cloud API (Windows / macOS / Linux)
Author: Ruben Phagura
Author-email: contact@rubenphagura.com
License: GNU General Public License (GPL)
Project-URL: Source, https://github.com/ruben2163/groqchat
Project-URL: Tracker, https://github.com/ruben2163/groqchat/issues
Project-URL: Documentation, https://github.com/ruben2163/groqchat/wiki
Keywords: ai google gemini palm codey vertex api multimodal vision
Classifier: Development Status :: 5 - Production/Stable
Classifier: Intended Audience :: End Users/Desktop
Classifier: Topic :: Utilities
Classifier: License :: OSI Approved :: GNU General Public License v3 or later (GPLv3+)
Classifier: Programming Language :: Python :: 3.8
Classifier: Programming Language :: Python :: 3.9
Classifier: Programming Language :: Python :: 3.10
Classifier: Programming Language :: Python :: 3.11
Classifier: Programming Language :: Python :: 3.12
Requires-Python: >=3.8
Requires-Dist: prompt_toolkit
Requires-Dist: groq
Requires-Dist: soundfile==0.12.1
Requires-Dist: sounddevice==0.4.7
Requires-Dist: SpeechRecognition
Requires-Dist: psutil
Requires-Dist: requests
Requires-Dist: numpy==1.26.4
Dynamic: author
Dynamic: author-email
Dynamic: classifier
Dynamic: description
Dynamic: keywords
Dynamic: license
Dynamic: project-url
Dynamic: requires-dist
Dynamic: requires-python
Dynamic: summary
